brightway25/__init__.py
brightway25-1.1.0.dist-info/LICENSE
brightway25-1.1.0.dist-info/METADATA
brightway25-1.1.0.dist-info/WHEEL
brightway25-1.1.0.dist-info/top_level.txt
brightway25-1.1.0.dist-info/RECORD
