Metadata-Version: 2.2
Name: brightway25
Version: 1.1.0
Summary: A wrapper library for documentation and easy installation of Brightway 2.5
Author-email: Chris Mutel <cmutel@gmail.com>
Maintainer-email: Chris Mutel <cmutel@gmail.com>
Project-URL: source, https://github.com/brightway-lca/brightway25
Project-URL: homepage, https://github.com/brightway-lca/brightway25
Project-URL: tracker, https://github.com/brightway-lca/brightway25/issues
Classifier: Development Status :: 4 - Beta
Classifier: Programming Language :: Python
Classifier: Programming Language :: Python :: 3
Classifier: Programming Language :: Python :: 3.9
Classifier: Programming Language :: Python :: 3.10
Classifier: Programming Language :: Python :: 3.11
Classifier: Programming Language :: Python :: 3.12
Classifier: Programming Language :: Python :: 3.13
Classifier: Natural Language :: English
Classifier: Operating System :: OS Independent
Classifier: Topic :: Scientific/Engineering
Requires-Python: >=3.9
License-File: LICENSE
Requires-Dist: bw2analyzer>=0.11.1
Requires-Dist: bw2calc>=2.0.1
Requires-Dist: bw2data>=4.4.2
Requires-Dist: bw2io>=0.9.6
Requires-Dist: bw2parameters>=1.1.0
Requires-Dist: bw_migrations>=0.2
Requires-Dist: bw_processing>=1.0
Requires-Dist: bw_simapro_csv>=0.4
Requires-Dist: ecoinvent_interface>=3.1
Requires-Dist: matrix_utils>=0.6
Requires-Dist: mrio_common_metadata>=0.2.1
Requires-Dist: multifunctional>=1.0
Requires-Dist: numpy<2
Requires-Dist: randonneur>=0.6.1
Requires-Dist: randonneur_data>=0.5.5
Requires-Dist: scipy
Requires-Dist: stats_arrays>=0.7
Provides-Extra: testing
Requires-Dist: brightway25; extra == "testing"
Requires-Dist: pytest; extra == "testing"
Requires-Dist: pytest-cov; extra == "testing"
Requires-Dist: python-coveralls; extra == "testing"
Provides-Extra: dev
Requires-Dist: build; extra == "dev"
Requires-Dist: pre-commit; extra == "dev"
Requires-Dist: pylint; extra == "dev"
Requires-Dist: pytest; extra == "dev"
Requires-Dist: pytest-cov; extra == "dev"
Requires-Dist: pytest-randomly; extra == "dev"
Requires-Dist: setuptools; extra == "dev"
